FQuant/Aggregates.py
FQuant/Aggregates.pyi
FQuant/DateCorr.py
FQuant/DateCorr.pyi
FQuant/Fetch_Trading_Data.py
FQuant/Fetch_Trading_Data.pyi
FQuant/FiinIndicator.py
FQuant/FiinIndicator.pyi
FQuant/FiinQuant.py
FQuant/FiinQuant.pyi
FQuant/RealTimeData.py
FQuant/RealTimeData.pyi
FQuant/Rebalance.py
FQuant/Rebalance.pyi
FQuant/SimilarChart.py
FQuant/SimilarChart.pyi
FQuant/Trading_Data_Stream.py
FQuant/Trading_Data_Stream.pyi
FQuant/__init__.py
FQuant/__init__.pyi
fquant-0.1.0.dist-info/METADATA
fquant-0.1.0.dist-info/WHEEL
fquant-0.1.0.dist-info/top_level.txt
fquant-0.1.0.dist-info/RECORD
